Octra/__init__.py
Octra/custom.py
Octra/entitycache.py
Octra/functions.py
Octra/helpers.py
Octra/hints.py
Octra/password.py
Octra/requestiter.py
Octra/sync.py
Octra/types.py
Octra/utils.py
Octra/version.py
Octra/_updates/__init__.py
Octra/_updates/entitycache.py
Octra/_updates/messagebox.py
Octra/_updates/session.py
Octra/client/__init__.py
Octra/client/account.py
Octra/client/auth.py
Octra/client/bots.py
Octra/client/buttons.py
Octra/client/chats.py
Octra/client/dialogs.py
Octra/client/downloads.py
Octra/client/messageparse.py
Octra/client/messages.py
Octra/client/telegrambaseclient.py
Octra/client/telegramclient.py
Octra/client/updates.py
Octra/client/uploads.py
Octra/client/users.py
Octra/crypto/__init__.py
Octra/crypto/aes.py
Octra/crypto/aesctr.py
Octra/crypto/authkey.py
Octra/crypto/cdndecrypter.py
Octra/crypto/factorization.py
Octra/crypto/libssl.py
Octra/crypto/rsa.py
Octra/errors/__init__.py
Octra/errors/common.py
Octra/errors/rpcbaseerrors.py
Octra/errors/rpcerrorlist.py
Octra/events/__init__.py
Octra/events/album.py
Octra/events/callbackquery.py
Octra/events/chataction.py
Octra/events/common.py
Octra/events/inlinequery.py
Octra/events/messagedeleted.py
Octra/events/messageedited.py
Octra/events/messageread.py
Octra/events/newmessage.py
Octra/events/raw.py
Octra/events/userupdate.py
Octra/extensions/__init__.py
Octra/extensions/binaryreader.py
Octra/extensions/html.py
Octra/extensions/markdown.py
Octra/extensions/messagepacker.py
Octra/network/__init__.py
Octra/network/authenticator.py
Octra/network/mtprotoplainsender.py
Octra/network/mtprotosender.py
Octra/network/mtprotostate.py
Octra/network/requeststate.py
Octra/network/connection/__init__.py
Octra/network/connection/connection.py
Octra/network/connection/http.py
Octra/network/connection/tcpabridged.py
Octra/network/connection/tcpfull.py
Octra/network/connection/tcpintermediate.py
Octra/network/connection/tcpmtproxy.py
Octra/network/connection/tcpobfuscated.py
Octra/sessions/__init__.py
Octra-1.1.4.dist-info/LICENSE
Octra-1.1.4.dist-info/METADATA
Octra-1.1.4.dist-info/WHEEL
Octra-1.1.4.dist-info/top_level.txt
Octra-1.1.4.dist-info/RECORD
